openapi_parser/__init__.py
openapi_parser/__main__.py
openapi_parser/cli.py
openapi_parser/model.py
openapi_parser/exporter/__init__.py
openapi_parser/exporter/abstract_writer.py
openapi_parser/exporter/attribute_writer.py
openapi_parser/exporter/class_writer.py
openapi_parser/exporter/client_writer.py
openapi_parser/exporter/description_writer.py
openapi_parser/exporter/footer_writer.py
openapi_parser/exporter/header_writer.py
openapi_parser/exporter/inspect_writer.py
openapi_parser/exporter/method_writer.py
openapi_parser/exporter/model_writer.py
openapi_parser/exporter/pacakge_init_writer.py
openapi_parser/exporter/package_writer.py
openapi_parser/exporter/utils_writer.py
openapi_parser/exporter/exporting_features/__init__.py
openapi_parser/exporter/exporting_features/client.py
openapi_parser/exporter/exporting_features/utils.py
openapi_parser/parser/__init__.py
openapi_parser/parser/date_formats.py
openapi_parser/parser/errors.py
openapi_parser/parser/filters.py
openapi_parser/parser/inheritance_support.py
openapi_parser/parser/loader.py
openapi_parser/parser/model_impl.py
openapi_parser/parser/path.py
openapi_parser/util/__init__.py
openapi_parser/util/_backports.py
openapi_parser/util/naming_conventions.py
openapi_parser/util/typing_proxy.py
openapi_parser/util/utils.py
openapi_parser-0.2.6.dist-info/LICENSE
openapi_parser-0.2.6.dist-info/METADATA
openapi_parser-0.2.6.dist-info/WHEEL
openapi_parser-0.2.6.dist-info/namespace_packages.txt
openapi_parser-0.2.6.dist-info/top_level.txt
openapi_parser-0.2.6.dist-info/RECORD
