Metadata-Version: 2.1
Name: openapi-parser
Version: 0.2.6
Summary: OpenAPI 3.0 specs parser and client/server generator
Home-page: https://gitlab.com/Hares-Lab/openapi-parser
License: BSD 2-Clause License
Platform: UNKNOWN
Classifier: Development Status :: 2 - Pre-Alpha
Classifier: License :: OSI Approved :: BSD License
Classifier: Intended Audience :: Developers
Classifier: Natural Language :: English
Classifier: Operating System :: OS Independent
Classifier: Programming Language :: Python :: 3.6
Classifier: Programming Language :: Python :: 3.7
Classifier: Programming Language :: Python :: 3.8
Classifier: Programming Language :: Python :: 3.9
Classifier: Topic :: Software Development :: Code Generators
Classifier: Topic :: Software Development :: Libraries
Classifier: Topic :: Software Development :: Libraries :: Python Modules
Classifier: Topic :: Utilities
Requires-Python: >=3.6.0
License-File: LICENSE
Requires-Dist: dataclasses-json (>=0.5.2)
Requires-Dist: functional-python (>=0.0.9)
Requires-Dist: http-server-base (>=2.0.1)
Requires-Dist: PyYAML (~=5.3.1)
Requires-Dist: stringcase (<2.0.0,==1.2.0)
Requires-Dist: tornado (>=6.0.4)
Requires-Dist: license (==0.1a3)
Requires-Dist: dataclasses (>=0.7) ; python_version < "3.7"
Requires-Dist: lazy-object-proxy (==1.5.1) ; python_version < "3.8"
Provides-Extra: all
